zklibweb/__init__.py
zklibweb/client.py
zklibweb/domain.py
zklibweb/exceptions.py
zklibweb/utils.py
zklibweb-0.3.2.dist-info/METADATA
zklibweb-0.3.2.dist-info/WHEEL
zklibweb-0.3.2.dist-info/top_level.txt
zklibweb-0.3.2.dist-info/RECORD
